varphi_python/__init__.py
varphi_python/cli.py
varphi_python/compiler.py
varphi_python/lib/__init__.py
varphi_python/lib/exceptions.py
varphi_python/lib/functions.py
varphi_python/lib/io.py
varphi_python/lib/model.py
varphi_python-2.0.6.dist-info/WHEEL
varphi_python-2.0.6.dist-info/entry_points.txt
varphi_python-2.0.6.dist-info/METADATA
varphi_python-2.0.6.dist-info/RECORD
